testHelloWorldpkg/__init__.py
testHelloWorldpkg/app.py
testHelloWorldpkg/utils/__init__.py
testHelloWorldpkg/utils/data.py
testHelloWorldpkg-0.0.6.dist-info/METADATA
testHelloWorldpkg-0.0.6.dist-info/WHEEL
testHelloWorldpkg-0.0.6.dist-info/top_level.txt
testHelloWorldpkg-0.0.6.dist-info/RECORD
