Metadata-Version: 2.1
Name: testHelloWorldpkg
Version: 0.0.6
Summary: A Hello world pkg
Home-page: 
Author: Moshiur
Author-email: 
Classifier: Programming Language :: Python :: 3
Classifier: License :: OSI Approved :: MIT License
Classifier: Operating System :: OS Independent
Requires-Python: >=3.9
